[
    {
        "name": "Wolf",
        "relations": {
            "Boa": 0,
            "Fox": 0,
            "Bear": 0,
            "Eagle": 0,
            "Horse": 10,
            "Deer": 15,
            "Rabbit": 60,
            "Mouse": 80,
            "Goat": 60,
            "Sheep": 70,
            "Boar": 15,
            "Buffalo": 10,
            "Duck": 40,
            "Caterpillar": 0
        }
    },
    {
        "name": "Boa",
        "relations": {
            "Wolf": 0,
            "Fox": 15,
            "Bear": 0,
            "Eagle": 0,
            "Horse": 0,
            "Deer": 0,
            "Rabbit": 20,
            "Mouse": 40,
            "Goat": 0,
            "Sheep": 0,
            "Boar": 0,
            "Buffalo": 0,
            "Duck": 10,
            "Caterpillar": 0
        }
    },
    {
        "name": "Fox",
        "relations": {
            "Wolf": 0,
            "Boa": 0,
            "Bear": 0,
            "Eagle": 10,
            "Horse": 0,
            "Deer": 0,
            "Rabbit": 70,
            "Mouse": 90,
            "Goat": 0,
            "Sheep": 0,
            "Boar": 0,
            "Buffalo": 0,
            "Duck": 60,
            "Caterpillar": 40
        }
    },
    {
        "name": "Bear",
        "relations": {
            "Wolf": 0,
            "Boa": 80,
            "Fox": 0,
            "Eagle": 0,
            "Horse": 40,
            "Deer": 80,
            "Rabbit": 80,
            "Mouse": 90,
            "Goat": 70,
            "Sheep": 70,
            "Boar": 50,
            "Buffalo": 20,
            "Duck": 10,
            "Caterpillar": 0
        }
    },
    {
        "name": "Eagle",
        "relations": {
            "Wolf": 0,
            "Boa": 0,
            "Fox": 10,
            "Bear": 0,
            "Horse": 0,
            "Deer": 0,
            "Rabbit": 90,
            "Mouse": 90,
            "Goat": 0,
            "Sheep": 0,
            "Boar": 0,
            "Buffalo": 0,
            "Duck": 80,
            "Caterpillar": 0
        }
    },
    {
        "name": "Horse",
        "relations": {
            "Wolf": 0,
            "Boa": 0,
            "Fox": 0,
            "Bear": 0,
            "Eagle": 0,
            "Deer": 0,
            "Rabbit": 0,
            "Mouse": 0,
            "Goat": 0,
            "Sheep": 0,
            "Boar": 0,
            "Buffalo": 0,
            "Duck": 0,
            "Caterpillar": 0
        }
    },
    {
        "name": "Deer",
        "relations": {
            "Wolf": 0,
            "Boa": 0,
            "Fox": 0,
            "Bear": 0,
            "Eagle": 0,
            "Horse": 0,
            "Rabbit": 0,
            "Mouse": 0,
            "Goat": 0,
            "Sheep": 0,
            "Boar": 0,
            "Buffalo": 0,
            "Duck": 0,
            "Caterpillar": 0
        }
    },
    {
        "name": "Rabbit",
        "relations": {
            "Wolf": 0,
            "Boa": 0,
            "Fox": 0,
            "Bear": 0,
            "Eagle": 0,
            "Horse": 0,
            "Deer": 0,
            "Mouse": 0,
            "Goat": 0,
            "Sheep": 0,
            "Boar": 0,
            "Buffalo": 0,
            "Duck": 0,
            "Caterpillar": 0
        }
    },
    {
        "name": "Mouse",
        "relations": {
            "Wolf": 0,
            "Boa": 0,
            "Fox": 0,
            "Bear": 0,
            "Eagle": 0,
            "Horse": 0,
            "Deer": 0,
            "Rabbit": 0,
            "Goat": 0,
            "Sheep": 0,
            "Boar": 0,
            "Buffalo": 0,
            "Duck": 0,
            "Caterpillar": 90
        }
    },
    {
        "name": "Goat",
        "relations": {
            "Wolf": 0,
            "Boa": 0,
            "Fox": 0,
            "Bear": 0,
            "Eagle": 0,
            "Horse": 0,
            "Deer": 0,
            "Rabbit": 0,
            "Mouse": 0,
            "Sheep": 0,
            "Boar": 0,
            "Buffalo": 0,
            "Duck": 0,
            "Caterpillar": 0
        }
    },
    {
        "name": "Sheep",
        "relations": {
            "Wolf": 0,
            "Boa": 0,
            "Fox": 0,
            "Bear": 0,
            "Eagle": 0,
            "Horse": 0,
            "Deer": 0,
            "Rabbit": 0,
            "Mouse": 0,
            "Goat": 0,
            "Boar": 0,
            "Buffalo": 0,
            "Duck": 0,
            "Caterpillar": 0
        }
    },
    {
        "name": "Boar",
        "relations": {
            "Wolf": 0,
            "Boa": 0,
            "Fox": 0,
            "Bear": 0,
            "Eagle": 0,
            "Horse": 0,
            "Deer": 0,
            "Rabbit": 0,
            "Mouse": 50,
            "Goat": 0,
            "Sheep": 0,
            "Buffalo": 0,
            "Duck": 0,
            "Caterpillar": 90
        }
    },
    {
        "name": "Buffalo",
        "relations": {
            "Wolf": 0,
            "Boa": 0,
            "Fox": 0,
            "Bear": 0,
            "Eagle": 0,
            "Horse": 0,
            "Deer": 0,
            "Rabbit": 0,
            "Mouse": 0,
            "Goat": 0,
            "Sheep": 0,
            "Boar": 0,
            "Duck": 0,
            "Caterpillar": 0
        }
    },
    {
        "name": "Duck",
        "relations": {
            "Wolf": 0,
            "Boa": 0,
            "Fox": 0,
            "Bear": 0,
            "Eagle": 0,
            "Horse": 0,
            "Deer": 0,
            "Rabbit": 0,
            "Mouse": 0,
            "Goat": 0,
            "Sheep": 0,
            "Boar": 0,
            "Buffalo": 0,
            "Caterpillar": 90
        }
    },
    {
        "name": "Caterpillar",
        "relations": {
            "Wolf": 0,
            "Boa": 0,
            "Fox": 0,
            "Bear": 0,
            "Eagle": 0,
            "Horse": 0,
            "Deer": 0,
            "Rabbit": 0,
            "Mouse": 0,
            "Goat": 0,
            "Sheep": 0,
            "Boar": 0,
            "Buffalo": 0,
            "Duck": 0
        }
    }
]
